craft_store/__init__.py
craft_store/_httpx_auth.py
craft_store/_version.py
craft_store/attenuations.py
craft_store/auth.py
craft_store/base_client.py
craft_store/creds.py
craft_store/endpoints.py
craft_store/errors.py
craft_store/http_client.py
craft_store/py.typed
craft_store/store_client.py
craft_store/ubuntu_one_store_client.py
craft_store/models/__init__.py
craft_store/models/_base_model.py
craft_store/models/_charm_model.py
craft_store/models/_common_list_releases_model.py
craft_store/models/_snap_models.py
craft_store/models/account_model.py
craft_store/models/charm_list_releases_model.py
craft_store/models/error_model.py
craft_store/models/registered_name_model.py
craft_store/models/release_request_model.py
craft_store/models/resource_revision_model.py
craft_store/models/revisions_model.py
craft_store/models/snap_list_releases_model.py
craft_store/models/track_guardrail_model.py
craft_store/models/track_model.py
craft_store/publisher/__init__.py
craft_store/publisher/_publishergw.py
craft_store/publisher/_request.py
craft_store/publisher/_response.py
craft_store-3.3.0.dist-info/LICENSE
craft_store-3.3.0.dist-info/METADATA
craft_store-3.3.0.dist-info/WHEEL
craft_store-3.3.0.dist-info/top_level.txt
craft_store-3.3.0.dist-info/RECORD
